{
  "generated_at": "2026-04-20T01:15:55.091656+00:00",
  "docs_root": "/Users/gdc/stoa/docs/design",
  "doc_count": 168,
  "date_range": {
    "first": "2025-01-16",
    "last": "2026-04-18"
  },
  "themes": [
    {
      "theme": "crdt",
      "doc_count": 26,
      "total_lines": 18565,
      "samples": [
        {
          "title": "Web Rename as Delete + Create",
          "date": "2026-04-16",
          "file": "2026-04-16-WEB-RENAME-AS-DELETE-PLUS-CREATE.md"
        },
        {
          "title": "Intent CLI Node Bridge Parity Design",
          "date": "2026-03-31",
          "file": "2026-03-31-INTENT-CLI-NODE-BRIDGE-PARITY.md"
        },
        {
          "title": "Lessons from tnyOffice Implementation",
          "date": "2026-03-31",
          "file": "LESSONS-FROM-TNYOFFICE.md"
        }
      ]
    },
    {
      "theme": "agents",
      "doc_count": 40,
      "total_lines": 29086,
      "samples": [
        {
          "title": "Community Forum Design (Discourse-Style, Cross-Org + Public)",
          "date": "2026-04-16",
          "file": "2026-04-16-COMMUNITY-FORUM-DESIGN.md"
        },
        {
          "title": "Credit Expiration and Non-Refundable Policy",
          "date": "2026-04-14",
          "file": "2026-04-14-CREDIT-EXPIRATION-AND-NON-REFUNDABLE.md"
        },
        {
          "title": "Live CLI Agent Presence in Meetings",
          "date": "2026-04-13",
          "file": "2026-04-13-LIVE-CLI-AGENT-PRESENCE-IN-MEETINGS.md"
        }
      ]
    },
    {
      "theme": "ui_ux",
      "doc_count": 12,
      "total_lines": 5836,
      "samples": [
        {
          "title": "Restore to This Version — UX Plan",
          "date": "2026-04-17",
          "file": "2026-04-17-RESTORE-VERSION-UX.md"
        },
        {
          "title": "Timeline Tab Implementation Design",
          "date": "2026-03-31",
          "file": "2025-11-14_TIMELINE_DESIGN.md"
        },
        {
          "title": "Focus Docs & Topics UX Fixes",
          "date": "2026-03-25",
          "file": "2026-03-25-FOCUS-DOCS-TOPICS-UX-FIXES.md"
        }
      ]
    },
    {
      "theme": "p2p_sync",
      "doc_count": 18,
      "total_lines": 9950,
      "samples": [
        {
          "title": "1. Create the Fly app (once)",
          "date": "2026-03-31",
          "file": "FLYIO.MD"
        },
        {
          "title": "Multi-User Markdown Collaboration",
          "date": "2026-03-31",
          "file": "MULTI-USER-MARKDOWN-SYNC.md"
        },
        {
          "title": "True Sync Status Indicator Design",
          "date": "2026-01-20",
          "file": "2026-01-20-TRUE-SYNC-STATUS-INDICATOR.md"
        }
      ]
    },
    {
      "theme": "version_history",
      "doc_count": 12,
      "total_lines": 6698,
      "samples": [
        {
          "title": "Timeline Tab Implementation Design",
          "date": "2026-03-31",
          "file": "2025-11-14_TIMELINE_DESIGN.md"
        },
        {
          "title": "Version History Expand Behavior Improvements",
          "date": "2026-01-27",
          "file": "2026-01-27-VERSION-HISTORY-EXPAND-BEHAVIOR.md"
        },
        {
          "title": "Integrated Arena UI Design",
          "date": "2025-12-30",
          "file": "2025-12-30-INTEGRATED-ARENA-UI.md"
        }
      ]
    },
    {
      "theme": "meetings_voice",
      "doc_count": 21,
      "total_lines": 10321,
      "samples": [
        {
          "title": "Live CLI Agent Presence in Meetings",
          "date": "2026-04-13",
          "file": "2026-04-13-LIVE-CLI-AGENT-PRESENCE-IN-MEETINGS.md"
        },
        {
          "title": "Workthreads — Final Design",
          "date": "2026-04-08",
          "file": "2026-04-08-WORKTHREADS-V1-PLAN.md"
        },
        {
          "title": "Workthreads",
          "date": "2026-04-06",
          "file": "2026-04-06-WORKTHREADS.md"
        }
      ]
    },
    {
      "theme": "billing_auth",
      "doc_count": 3,
      "total_lines": 1433,
      "samples": [
        {
          "title": "Credit Expiration and Non-Refundable Policy",
          "date": "2026-04-14",
          "file": "2026-04-14-CREDIT-EXPIRATION-AND-NON-REFUNDABLE.md"
        },
        {
          "title": "Unified Auth Refactor Design",
          "date": "2026-03-24",
          "file": "2026-03-24-UNIFIED-AUTH-REFACTOR-DESIGN.md"
        },
        {
          "title": "Automerge Relay Compatibility Notes",
          "date": "2025-10-12",
          "file": "2025-10-12-AUTOMERGE-RELAY-COMPATIBILITY.md"
        }
      ]
    },
    {
      "theme": "desktop",
      "doc_count": 6,
      "total_lines": 2794,
      "samples": [
        {
          "title": "Transcription Excellence: Ideas from Minutes for Intent",
          "date": "2026-03-29",
          "file": "2026-03-29-TRANSCRIPTION-EXCELLENCE-FROM-MINUTES.md"
        },
        {
          "title": "Arena Habit Loop and Dependency Design",
          "date": "2026-02-13",
          "file": "2026-02-13-ARENA-HABIT-LOOP-AND-DEPENDENCY-DESIGN.md"
        },
        {
          "title": "Full File Tree Per Exchange - Desktop GUI Design",
          "date": "2025-10-15",
          "file": "2025-10-15-FULL-FILE-TREE-PER-EXCHANGE.md"
        }
      ]
    },
    {
      "theme": "cli_terminal",
      "doc_count": 18,
      "total_lines": 7611,
      "samples": [
        {
          "title": "Web Rename as Delete + Create",
          "date": "2026-04-16",
          "file": "2026-04-16-WEB-RENAME-AS-DELETE-PLUS-CREATE.md"
        },
        {
          "title": "Live CLI Agent Presence in Meetings",
          "date": "2026-04-13",
          "file": "2026-04-13-LIVE-CLI-AGENT-PRESENCE-IN-MEETINGS.md"
        },
        {
          "title": "Intent CLI Node Bridge Parity Design",
          "date": "2026-03-31",
          "file": "2026-03-31-INTENT-CLI-NODE-BRIDGE-PARITY.md"
        }
      ]
    },
    {
      "theme": "platform_arch",
      "doc_count": 52,
      "total_lines": 37109,
      "samples": [
        {
          "title": "Web Rename as Delete + Create",
          "date": "2026-04-16",
          "file": "2026-04-16-WEB-RENAME-AS-DELETE-PLUS-CREATE.md"
        },
        {
          "title": "Onboarding Email Architecture",
          "date": "2026-04-07",
          "file": "2026-04-07-ONBOARDING-EMAIL-ARCHITECTURE.md"
        },
        {
          "title": "Web Feature Flags with Vercel Flags SDK",
          "date": "2026-04-07",
          "file": "2026-04-07-WEB-FEATURE-FLAGS-VERCEL-SDK.md"
        }
      ]
    },
    {
      "theme": "community_forum",
      "doc_count": 2,
      "total_lines": 1850,
      "samples": [
        {
          "title": "Community Forum IA Mocks",
          "date": "2026-04-18",
          "file": "2026-04-18-COMMUNITY-FORUM-IA-MOCKS.md"
        },
        {
          "title": "Community Forum Design (Discourse-Style, Cross-Org + Public)",
          "date": "2026-04-16",
          "file": "2026-04-16-COMMUNITY-FORUM-DESIGN.md"
        }
      ]
    },
    {
      "theme": "provenance",
      "doc_count": 4,
      "total_lines": 2263,
      "samples": [
        {
          "title": "Arena Workspace Provenance Design",
          "date": "2026-01-26",
          "file": "2026-01-26-ARENA-LIVE-EDITING-DRAFT-DOC.md"
        },
        {
          "title": "Provenance-Git Separation Design",
          "date": "2026-01-25",
          "file": "2026-01-25-EXPANDED-INTENT-GIT.md"
        },
        {
          "title": "Provenance from CRDT Marks Design",
          "date": "2025-12-29",
          "file": "2025-12-29-PROVENANCE-FROM-CRDT-MARKS.md"
        }
      ]
    },
    {
      "theme": "other",
      "doc_count": 34,
      "total_lines": 18069,
      "samples": [
        {
          "title": "Pre-Launch Performance KISS Plan",
          "date": "2026-04-14",
          "file": "2026-04-14-PRELAUNCH-PERFORMANCE-KISS-PLAN.md"
        },
        {
          "title": "Team Invite & Activation Strategy",
          "date": "2026-04-10",
          "file": "2026-04-10-TEAM-INVITE-AND-ACTIVATION-STRATEGY.md"
        },
        {
          "title": "HTML Renderer — Relative Asset Resolution",
          "date": "2026-04-07",
          "file": "2026-04-07-HTML-RENDERER-RELATIVE-ASSET-RESOLUTION.md"
        }
      ]
    }
  ],
  "by_month": [
    {
      "month": "2025-01",
      "count": 2
    },
    {
      "month": "2025-09",
      "count": 22
    },
    {
      "month": "2025-10",
      "count": 23
    },
    {
      "month": "2025-11",
      "count": 17
    },
    {
      "month": "2025-12",
      "count": 20
    },
    {
      "month": "2026-01",
      "count": 13
    },
    {
      "month": "2026-02",
      "count": 13
    },
    {
      "month": "2026-03",
      "count": 38
    },
    {
      "month": "2026-04",
      "count": 20
    }
  ],
  "top_terms": [
    {
      "term": "intent",
      "count": 3901
    },
    {
      "term": "agent",
      "count": 2853
    },
    {
      "term": "session",
      "count": 2389
    },
    {
      "term": "string",
      "count": 1750
    },
    {
      "term": "project",
      "count": 1705
    },
    {
      "term": "crdt",
      "count": 1635
    },
    {
      "term": "automerge",
      "count": 1399
    },
    {
      "term": "code",
      "count": 1368
    },
    {
      "term": "sync",
      "count": 1190
    },
    {
      "term": "text",
      "count": 1186
    },
    {
      "term": "time",
      "count": 1163
    },
    {
      "term": "type",
      "count": 1159
    },
    {
      "term": "server",
      "count": 1148
    },
    {
      "term": "changes",
      "count": 1146
    },
    {
      "term": "document",
      "count": 1079
    },
    {
      "term": "content",
      "count": 1067
    },
    {
      "term": "create",
      "count": 1040
    },
    {
      "term": "json",
      "count": 1026
    },
    {
      "term": "exchange",
      "count": 982
    },
    {
      "term": "auth",
      "count": 946
    },
    {
      "term": "return",
      "count": 912
    },
    {
      "term": "arena",
      "count": 897
    },
    {
      "term": "context",
      "count": 895
    },
    {
      "term": "episode",
      "count": 890
    },
    {
      "term": "state",
      "count": 878
    }
  ],
  "files": [
    {
      "file": "2025-01-16-TUI-DESIGN.md",
      "title": "TUI Design for Intent Commands",
      "date": "2025-01-16",
      "lines": 178,
      "themes": [
        "cli_terminal"
      ]
    },
    {
      "file": "2025-01-28-INTERACTIVE-SHELL-DESIGN.md",
      "title": "Intent Interactive Shell: Architecture Design",
      "date": "2025-01-28",
      "lines": 2151,
      "themes": [
        "agents",
        "cli_terminal",
        "platform_arch"
      ]
    },
    {
      "file": "2025-09-15-AI_FILE_VERSIONING_DESIGN.md",
      "title": "AI-Aware File Versioning System Using Automerge-Repo",
      "date": "2025-09-15",
      "lines": 346,
      "themes": [
        "crdt",
        "cli_terminal",
        "platform_arch"
      ]
    },
    {
      "file": "2025-09-15-CLI_PORCELAIN_DESIGN.md",
      "title": "Better CLI Porcelain Design",
      "date": "2025-09-15",
      "lines": 660,
      "themes": [
        "cli_terminal"
      ]
    },
    {
      "file": "2025-09-16-AI_FILE_VERSIONING_EXPLAINED.md",
      "title": "Understanding the AI-Aware File Versioning System",
      "date": "2025-09-16",
      "lines": 295,
      "themes": [
        "other"
      ]
    },
    {
      "file": "2025-09-16-ARCHITECTURE_SCENARIOS.md",
      "title": "Architecture Scenarios for Multi-Process CRDT Access",
      "date": "2025-09-16",
      "lines": 335,
      "themes": [
        "crdt",
        "platform_arch"
      ]
    },
    {
      "file": "2025-09-16-ARCHITECTURE_TRADEOFFS_SUMMARY.md",
      "title": "Architecture Tradeoffs Summary",
      "date": "2025-09-16",
      "lines": 109,
      "themes": [
        "platform_arch"
      ]
    },
    {
      "file": "2025-09-16-AS-BUILT-ARCHITECTURE.md",
      "title": "AS-BUILT Architecture",
      "date": "2025-09-16",
      "lines": 109,
      "themes": [
        "crdt",
        "platform_arch"
      ]
    },
    {
      "file": "2025-09-16-AUTOMATIC_FILE_MOVE_SOLUTION.md",
      "title": "Automatic File Move Detection Solution",
      "date": "2025-09-16",
      "lines": 67,
      "themes": [
        "platform_arch"
      ]
    },
    {
      "file": "2025-09-16-AUTOMERGE_METADATA_RESEARCH.md",
      "title": "Automerge Metadata Research",
      "date": "2025-09-16",
      "lines": 126,
      "themes": [
        "crdt"
      ]
    },
    {
      "file": "2025-09-16-FILE_MOVE_HANDLING.md",
      "title": "File Move/Rename Handling",
      "date": "2025-09-16",
      "lines": 56,
      "themes": [
        "other"
      ]
    },
    {
      "file": "2025-09-16-FILE_OPERATIONS_STRATEGY.md",
      "title": "File Operations Implementation Strategy",
      "date": "2025-09-16",
      "lines": 137,
      "themes": [
        "other"
      ]
    },
    {
      "file": "2025-09-16-FILE_SYSTEM_OPERATIONS.md",
      "title": "File System Operations Analysis",
      "date": "2025-09-16",
      "lines": 151,
      "themes": [
        "crdt"
      ]
    },
    {
      "file": "2025-09-16-IPC_ARCHITECTURE_DESIGN.md",
      "title": "IPC Architecture Design",
      "date": "2025-09-16",
      "lines": 305,
      "themes": [
        "cli_terminal",
        "platform_arch"
      ]
    },
    {
      "file": "2025-09-16-IPC_FUTURE_EVOLUTION.md",
      "title": "IPC Architecture: Future Evolution Path",
      "date": "2025-09-16",
      "lines": 292,
      "themes": [
        "platform_arch"
      ]
    },
    {
      "file": "2025-09-16-MULTI_PROCESS_SYNC_ISSUE.md",
      "title": "Multi-Process Synchronization Issue with NodeFSStorageAdapter",
      "date": "2025-09-16",
      "lines": 132,
      "themes": [
        "cli_terminal",
        "platform_arch"
      ]
    },
    {
      "file": "2025-09-16-RESTORE_AND_GLOBAL_HISTORY_DESIGN.md",
      "title": "File Restore and Global History Design",
      "date": "2025-09-16",
      "lines": 215,
      "themes": [
        "other"
      ]
    },
    {
      "file": "2025-09-16-SPECSTORY_INTEGRATION_PLAN.md",
      "title": "SpecStory Integration Plan",
      "date": "2025-09-16",
      "lines": 319,
      "themes": [
        "platform_arch"
      ]
    },
    {
      "file": "2025-09-17-AS-BUILT-ARCHITECTURE.md",
      "title": "AS-BUILT Architecture",
      "date": "2025-09-17",
      "lines": 321,
      "themes": [
        "crdt",
        "platform_arch"
      ]
    },
    {
      "file": "2025-09-17-INTENT-VS-GIT.md",
      "title": "Intent vs Git: Version Control Comparison",
      "date": "2025-09-17",
      "lines": 107,
      "themes": [
        "other"
      ]
    },
    {
      "file": "2025-09-17-P2P-IMPLEMENTATION-GUIDE.md",
      "title": "P2P Network Implementation Guide",
      "date": "2025-09-17",
      "lines": 1055,
      "themes": [
        "p2p_sync"
      ]
    },
    {
      "file": "2025-09-17-P2P-MVP-ESSENTIALS.md",
      "title": "P2P MVP Essentials: Minimum Requirements for Two-Developer Collaboration",
      "date": "2025-09-17",
      "lines": 362,
      "themes": [
        "p2p_sync"
      ]
    },
    {
      "file": "2025-09-17-P2P-NETWORK-ARCHITECTURE.md",
      "title": "P2P Network Architecture for Intent",
      "date": "2025-09-17",
      "lines": 497,
      "themes": [
        "p2p_sync",
        "platform_arch"
      ]
    },
    {
      "file": "2025-09-17-PHASED-P2P-IMPLEMENTATION-PLAN.md",
      "title": "Phased P2P Implementation Plan: Tailscale to Relay Server",
      "date": "2025-09-17",
      "lines": 1118,
      "themes": [
        "p2p_sync"
      ]
    },
    {
      "file": "2025-10-05-intent-web-platform-design.md",
      "title": "Intent Web Platform Design Document",
      "date": "2025-10-05",
      "lines": 1634,
      "themes": [
        "other"
      ]
    },
    {
      "file": "2025-10-10-DECISION-TIMELINE-DESIGN.md",
      "title": "Decision Timeline Feature Design",
      "date": "2025-10-10",
      "lines": 2246,
      "themes": [
        "version_history",
        "platform_arch"
      ]
    },
    {
      "file": "2025-10-10-crdt-relay-scenarios.md",
      "title": "CRDT Relay MVP Scenarios",
      "date": "2025-10-10",
      "lines": 129,
      "themes": [
        "crdt",
        "p2p_sync"
      ]
    },
    {
      "file": "2025-10-10-offline-catchup-plan.md",
      "title": "Offline Catchup & Offline Change Journaling Plan",
      "date": "2025-10-10",
      "lines": 142,
      "themes": [
        "p2p_sync",
        "platform_arch"
      ]
    },
    {
      "file": "2025-10-11-FUTURE-VISION-AND-ROADMAP.md",
      "title": "Intent: Future Vision and Comprehensive Roadmap",
      "date": "2025-10-11",
      "lines": 3154,
      "themes": [
        "other"
      ]
    },
    {
      "file": "2025-10-11-MIGRATE-TO-SINGLE-DAEMON.md",
      "title": "Migration to Single System-Wide Daemon",
      "date": "2025-10-11",
      "lines": 1032,
      "themes": [
        "platform_arch"
      ]
    },
    {
      "file": "2025-10-12-AUTOMERGE-RELAY-COMPATIBILITY.md",
      "title": "Automerge Relay Compatibility Notes",
      "date": "2025-10-12",
      "lines": 62,
      "themes": [
        "crdt",
        "p2p_sync",
        "billing_auth"
      ]
    },
    {
      "file": "2025-10-12-MAC-SYSTEM-TRAY-TASKS.md",
      "title": "Mac System Tray - MVP Tasks",
      "date": "2025-10-12",
      "lines": 214,
      "themes": [
        "desktop",
        "platform_arch"
      ]
    },
    {
      "file": "2025-10-12-RELAY-FIRST-MESSAGING-DESIGN.md",
      "title": "Relay-First Messaging Service Design",
      "date": "2025-10-12",
      "lines": 372,
      "themes": [
        "crdt",
        "p2p_sync"
      ]
    },
    {
      "file": "2025-10-12-TUI-SEARCH-ROADMAP.md",
      "title": "TUI Search & Collaboration North Star (2025-10-12)",
      "date": "2025-10-12",
      "lines": 42,
      "themes": [
        "version_history",
        "cli_terminal"
      ]
    },
    {
      "file": "2025-10-13-MAC-DESKTOP-APP-DESIGN.md",
      "title": "macOS Desktop Application Design",
      "date": "2025-10-13",
      "lines": 455,
      "themes": [
        "desktop"
      ]
    },
    {
      "file": "2025-10-13-MAIN-WINDOW-UI-OPTIONS.md",
      "title": "Main Window UI Implementation Options",
      "date": "2025-10-13",
      "lines": 527,
      "themes": [
        "ui_ux",
        "desktop"
      ]
    },
    {
      "file": "2025-10-15-FULL-FILE-TREE-PER-EXCHANGE.md",
      "title": "Full File Tree Per Exchange - Desktop GUI Design",
      "date": "2025-10-15",
      "lines": 659,
      "themes": [
        "desktop"
      ]
    },
    {
      "file": "2025-10-15-conversation-ledger.md",
      "title": "Conversational Ledger Architecture",
      "date": "2025-10-15",
      "lines": 142,
      "themes": [
        "platform_arch"
      ]
    },
    {
      "file": "2025-10-15-internet-service-options.md",
      "title": "Internet-Facing Intent Service: Vendor Options",
      "date": "2025-10-15",
      "lines": 183,
      "themes": [
        "platform_arch"
      ]
    },
    {
      "file": "2025-10-15-team-collaboration.md",
      "title": "Team Collaboration Flow",
      "date": "2025-10-15",
      "lines": 97,
      "themes": [
        "crdt",
        "platform_arch"
      ]
    },
    {
      "file": "2025-10-16-lsp-integration-architecture.md",
      "title": "Intent LSP Integration: Comprehensive Architectural Proposal",
      "date": "2025-10-16",
      "lines": 1516,
      "themes": [
        "agents",
        "platform_arch"
      ]
    },
    {
      "file": "2025-10-19-GIT-SYNC-EDGE-CASES.md",
      "title": "Git Sync Edge Cases and Special States",
      "date": "2025-10-19",
      "lines": 1147,
      "themes": [
        "p2p_sync"
      ]
    },
    {
      "file": "2025-10-20-RELEASE-CONTROL-IN-CRDT-WORLD.md",
      "title": "Release Control in a CRDT World",
      "date": "2025-10-20",
      "lines": 1278,
      "themes": [
        "crdt",
        "agents"
      ]
    },
    {
      "file": "2025-10-21-CRDT-STORAGE-APPROACHES.md",
      "title": "CRDT Storage Approaches: Compare and Contrast",
      "date": "2025-10-21",
      "lines": 1440,
      "themes": [
        "crdt",
        "platform_arch"
      ]
    },
    {
      "file": "2025-10-25-INTENT-VS-GIT-COMPREHENSIVE-ANALYSIS.md",
      "title": "Intent vs Git: Comprehensive Architecture Analysis",
      "date": "2025-10-25",
      "lines": 2169,
      "themes": [
        "crdt",
        "platform_arch"
      ]
    },
    {
      "file": "2025-10-25-STAGING-AND-BRANCHING-ANALYSIS.md",
      "title": "Intent Staging and Branching Analysis",
      "date": "2025-10-25",
      "lines": 2436,
      "themes": [
        "other"
      ]
    },
    {
      "file": "2025-10-28-posthog-helicone-instrumentation.md",
      "title": "2025-10-28 – PostHog & Helicone Instrumentation Plan",
      "date": "2025-10-28",
      "lines": 97,
      "themes": [
        "cli_terminal"
      ]
    },
    {
      "file": "2025-11-02-MULTI-AGENT-COORDINATION.md",
      "title": "Multi-Agent Coordination for Intent: Complete Implementation Guide",
      "date": "2025-11-02",
      "lines": 1214,
      "themes": [
        "agents",
        "platform_arch"
      ]
    },
    {
      "file": "2025-11-03-MULTI-AGENT-HOOK-INTEGRATION.md",
      "title": "Multi-Agent Coordination via Hook Integration",
      "date": "2025-11-03",
      "lines": 2197,
      "themes": [
        "agents",
        "platform_arch"
      ]
    },
    {
      "file": "2025-11-04-COLLABORATION-SESSIONS-DESIGN.md",
      "title": "Collaboration Sessions with LiveKit Integration",
      "date": "2025-11-04",
      "lines": 1740,
      "themes": [
        "meetings_voice",
        "platform_arch"
      ]
    },
    {
      "file": "2025-11-07-ARENA-DRIVE.md",
      "title": "Arena Drive: Managed Intent Workspace",
      "date": "2025-11-07",
      "lines": 506,
      "themes": [
        "agents"
      ]
    },
    {
      "file": "2025-11-07-CRDT-VS-GIT-COMPREHENSIVE-ANALYSIS.md",
      "title": "CRDTs vs Git for AI-Native Version Control: A Comprehensive Technical Analysis",
      "date": "2025-11-07",
      "lines": 3008,
      "themes": [
        "crdt"
      ]
    },
    {
      "file": "2025-11-07-INTENT-BASED-SEMANTIC-CONFLICT-DETECTION.md",
      "title": "Intent-Based Semantic Conflict Detection",
      "date": "2025-11-07",
      "lines": 785,
      "themes": [
        "other"
      ]
    },
    {
      "file": "2025-11-10-DASHBOARD-ARCHITECTURE.md",
      "title": "Intent Dashboard Architecture",
      "date": "2025-11-10",
      "lines": 247,
      "themes": [
        "platform_arch"
      ]
    },
    {
      "file": "2025-11-10-MARKDOWN-WEB-EDITOR.md",
      "title": "Markdown File Editing with Real-Time CRDT Sync",
      "date": "2025-11-10",
      "lines": 2208,
      "themes": [
        "crdt",
        "p2p_sync",
        "platform_arch"
      ]
    },
    {
      "file": "2025-11-10-SLACK-DOC-SYNC.md",
      "title": "Slack Documentation Sync Feature",
      "date": "2025-11-10",
      "lines": 593,
      "themes": [
        "p2p_sync"
      ]
    },
    {
      "file": "2025-11-11-SLACK-DOC-SYNC-AMENDMENT.md",
      "title": "Slack Doc Sync Amendment: Add Session-Thread Integration",
      "date": "2025-11-11",
      "lines": 189,
      "themes": [
        "p2p_sync"
      ]
    },
    {
      "file": "2025-11-12-version-history-design-variants.md",
      "title": "Version History Sidebar - Design Variants",
      "date": "2025-11-12",
      "lines": 234,
      "themes": [
        "version_history"
      ]
    },
    {
      "file": "2025-11-18-CREATE-EPISODE-FROM-EXCHANGE-REVISED.md",
      "title": "Create Episode from Exchange - Revised Design",
      "date": "2025-11-18",
      "lines": 351,
      "themes": [
        "version_history"
      ]
    },
    {
      "file": "2025-11-18-CREATE-EPISODE-FROM-EXCHANGE.md",
      "title": "Create Episode from Exchange State (MVP)",
      "date": "2025-11-18",
      "lines": 352,
      "themes": [
        "version_history"
      ]
    },
    {
      "file": "2025-11-18-VSCODE_FULL_EXCHANGE_FILE_TREE.md",
      "title": "VS Code Full Exchange File Tree Design (MVP)",
      "date": "2025-11-18",
      "lines": 263,
      "themes": [
        "other"
      ]
    },
    {
      "file": "2025-11-19-TIME-TRAVEL-TO-EXCHANGE.md",
      "title": "Time Travel to Exchange: Interactive Context Restoration",
      "date": "2025-11-19",
      "lines": 1088,
      "themes": [
        "cli_terminal"
      ]
    },
    {
      "file": "2025-11-19-VOICE-INTEGRATION-OPTIONS.md",
      "title": "Voice Integration Options for Intent Pairing Sessions",
      "date": "2025-11-19",
      "lines": 1665,
      "themes": [
        "meetings_voice"
      ]
    },
    {
      "file": "2025-11-25-CODEMIRROR-CURSOR-DATA-LOSS-FIXES.md",
      "title": "CodeMirror Cursor Jumping and Data Loss Fixes",
      "date": "2025-11-25",
      "lines": 856,
      "themes": [
        "ui_ux",
        "platform_arch"
      ]
    },
    {
      "file": "2025-12-02-FILE-BROWSER-ARCHITECTURE.md",
      "title": "File Browser Architecture",
      "date": "2025-12-02",
      "lines": 432,
      "themes": [
        "platform_arch"
      ]
    },
    {
      "file": "2025-12-04-POSTSYNC-ECHO-PREVENTION.md",
      "title": "PostSync Echo Prevention Design",
      "date": "2025-12-04",
      "lines": 89,
      "themes": [
        "p2p_sync",
        "platform_arch"
      ]
    },
    {
      "file": "2025-12-04-SESSION-CRDT-CREATION-AND-SYNC.md",
      "title": "Session CRDT Creation and Sync Architecture",
      "date": "2025-12-04",
      "lines": 614,
      "themes": [
        "crdt",
        "p2p_sync",
        "platform_arch"
      ]
    },
    {
      "file": "2025-12-05-MULTIPLAYER-DEMO-STORYBOARD.md",
      "title": "Making Agent Coding Multiplayer: Demo Video Storyboard",
      "date": "2025-12-05",
      "lines": 523,
      "themes": [
        "agents"
      ]
    },
    {
      "file": "2025-12-08-ARENA-WORKSPACE-ENTITY-MODEL.md",
      "title": "Arena Entity Model: Projects, Workspaces, and Collaboration Boundaries",
      "date": "2025-12-08",
      "lines": 1064,
      "themes": [
        "agents",
        "platform_arch"
      ]
    },
    {
      "file": "2025-12-08-checkpoint-system.md",
      "title": "Checkpoint System Design",
      "date": "2025-12-08",
      "lines": 812,
      "themes": [
        "agents",
        "version_history"
      ]
    },
    {
      "file": "2025-12-08-snapshot-store.md",
      "title": "Long-Term Snapshot Store Design",
      "date": "2025-12-08",
      "lines": 492,
      "themes": [
        "version_history",
        "provenance"
      ]
    },
    {
      "file": "2025-12-09-workspace-content-duplication-investigation.md",
      "title": "Workspace Content Duplication Investigation Plan",
      "date": "2025-12-09",
      "lines": 503,
      "themes": [
        "other"
      ]
    },
    {
      "file": "2025-12-10-document-list-push-events.md",
      "title": "Document List Push Events",
      "date": "2025-12-10",
      "lines": 257,
      "themes": [
        "platform_arch"
      ]
    },
    {
      "file": "2025-12-16-review-digest.md",
      "title": "Digest System Design",
      "date": "2025-12-16",
      "lines": 983,
      "themes": [
        "other"
      ]
    },
    {
      "file": "2025-12-17-INTENT-ADD-COMMAND.md",
      "title": "Intent Add Command Design",
      "date": "2025-12-17",
      "lines": 453,
      "themes": [
        "agents"
      ]
    },
    {
      "file": "2025-12-18-LAZY-LOADING-DESIGN.md",
      "title": "Lazy Loading Design for Intent-Web File Browser",
      "date": "2025-12-18",
      "lines": 381,
      "themes": [
        "crdt",
        "version_history"
      ]
    },
    {
      "file": "2025-12-18-snapshot-intent-review.md",
      "title": "Snapshot Intent Review",
      "date": "2025-12-18",
      "lines": 715,
      "themes": [
        "version_history"
      ]
    },
    {
      "file": "2025-12-19-TABLES-IN-PLACE-EDITING.md",
      "title": "In-Place Table Editing Design",
      "date": "2025-12-19",
      "lines": 402,
      "themes": [
        "other"
      ]
    },
    {
      "file": "2025-12-24-SCREEN-SHARE-OPTIMIZATION.md",
      "title": "Screen Share Optimization for Code Editors",
      "date": "2025-12-24",
      "lines": 170,
      "themes": [
        "meetings_voice"
      ]
    },
    {
      "file": "2025-12-29-DOCUMENT-TYPE-AND-SESSION-METADATA.md",
      "title": "Document Type and SessionID Metadata Design",
      "date": "2025-12-29",
      "lines": 430,
      "themes": [
        "p2p_sync"
      ]
    },
    {
      "file": "2025-12-29-PROVENANCE-FROM-CRDT-MARKS.md",
      "title": "Provenance from CRDT Marks Design",
      "date": "2025-12-29",
      "lines": 418,
      "themes": [
        "crdt",
        "provenance"
      ]
    },
    {
      "file": "2025-12-30-INTEGRATED-ARENA-UI.md",
      "title": "Integrated Arena UI Design",
      "date": "2025-12-30",
      "lines": 726,
      "themes": [
        "agents",
        "ui_ux",
        "version_history",
        "platform_arch"
      ]
    },
    {
      "file": "2025-12-30-MULTI-PROJECT-ARENA-DESIGN.md",
      "title": "Multi-Project Arena Design",
      "date": "2025-12-30",
      "lines": 628,
      "themes": [
        "agents",
        "platform_arch"
      ]
    },
    {
      "file": "2025-12-31-ALWAYS-ON-WORKSPACE.md",
      "title": "Always-On Arena Workspace Design",
      "date": "2025-12-31",
      "lines": 237,
      "themes": [
        "agents"
      ]
    },
    {
      "file": "2026-01-02-ARENA-DECISIONS-PAGE.md",
      "title": "Arena Decisions Page Design",
      "date": "2026-01-02",
      "lines": 721,
      "themes": [
        "agents",
        "meetings_voice"
      ]
    },
    {
      "file": "2026-01-07-COLLAB-WRITE-ARENA-DECISIONS.md",
      "title": "COLLAB_WRITE_ARENA_DECISIONS",
      "date": "2026-01-07",
      "lines": 625,
      "themes": [
        "agents",
        "meetings_voice"
      ]
    },
    {
      "file": "2026-01-07-LAZY-LIVEKIT-ROOM-CREATION.md",
      "title": "Lazy LiveKit Room Creation for Arena Workspaces",
      "date": "2026-01-07",
      "lines": 294,
      "themes": [
        "agents",
        "meetings_voice"
      ]
    },
    {
      "file": "2026-01-08-SESSION-FILES-TAB.md",
      "title": "Design: Session Files Tab in ProvenanceMapDialog",
      "date": "2026-01-08",
      "lines": 154,
      "themes": [
        "other"
      ]
    },
    {
      "file": "2026-01-09-MARK-BASED-COMMENTS.md",
      "title": "Plan: Mark-Based Comments for All File Types",
      "date": "2026-01-09",
      "lines": 214,
      "themes": [
        "other"
      ]
    },
    {
      "file": "2026-01-18-INVISIBLE-VERSION-CONTROL.md",
      "title": "Invisible Version Control: Intent's Vision for Seamless AI-Assisted Development",
      "date": "2026-01-18",
      "lines": 928,
      "themes": [
        "other"
      ]
    },
    {
      "file": "2026-01-20-TRUE-SYNC-STATUS-INDICATOR.md",
      "title": "True Sync Status Indicator Design",
      "date": "2026-01-20",
      "lines": 424,
      "themes": [
        "ui_ux",
        "p2p_sync"
      ]
    },
    {
      "file": "2026-01-21-MULTI-AGENT-COORDINATION-LEARNINGS-FROM-MULTICLAUDE.md",
      "title": "Multi-Agent Coordination: Architectural Learnings from multiclaude",
      "date": "2026-01-21",
      "lines": 1259,
      "themes": [
        "agents",
        "platform_arch"
      ]
    },
    {
      "file": "2026-01-21-TOOLBAR-AND-KEYBOARD-SHORTCUTS.md",
      "title": "Toolbar and Keyboard Shortcuts",
      "date": "2026-01-21",
      "lines": 149,
      "themes": [
        "ui_ux",
        "cli_terminal"
      ]
    },
    {
      "file": "2026-01-25-EXPANDED-INTENT-GIT.md",
      "title": "Provenance-Git Separation Design",
      "date": "2026-01-25",
      "lines": 947,
      "themes": [
        "provenance"
      ]
    },
    {
      "file": "2026-01-26-ARENA-LIVE-EDITING-DRAFT-DOC.md",
      "title": "Arena Workspace Provenance Design",
      "date": "2026-01-26",
      "lines": 406,
      "themes": [
        "agents",
        "platform_arch",
        "provenance"
      ]
    },
    {
      "file": "2026-01-27-VERSION-HISTORY-EXPAND-BEHAVIOR.md",
      "title": "Version History Expand Behavior Improvements",
      "date": "2026-01-27",
      "lines": 133,
      "themes": [
        "ui_ux",
        "version_history"
      ]
    },
    {
      "file": "2026-01-29-ARENA-AGENT-ARCHITECTURE.md",
      "title": "Arena Agent Architecture",
      "date": "2026-01-29",
      "lines": 1480,
      "themes": [
        "agents",
        "platform_arch"
      ]
    },
    {
      "file": "2026-02-13-ARENA-AGENT-FINAL-OPTIMIZATIONS.md",
      "title": "Arena Agent Final Optimizations (Reliability + Latency)",
      "date": "2026-02-13",
      "lines": 257,
      "themes": [
        "agents",
        "platform_arch"
      ]
    },
    {
      "file": "2026-02-13-ARENA-HABIT-LOOP-AND-DEPENDENCY-DESIGN.md",
      "title": "Arena Habit Loop and Dependency Design",
      "date": "2026-02-13",
      "lines": 341,
      "themes": [
        "agents",
        "desktop",
        "cli_terminal"
      ]
    },
    {
      "file": "2026-02-14-GITHUB-PROJECT-IMPORT.md",
      "title": "Add Project from GitHub",
      "date": "2026-02-14",
      "lines": 290,
      "themes": [
        "other"
      ]
    },
    {
      "file": "2026-02-17-COCRAFT-DESIGN-SYSTEM.md",
      "title": "Cocraft Design System",
      "date": "2026-02-17",
      "lines": 1798,
      "themes": [
        "ui_ux"
      ]
    },
    {
      "file": "2026-02-17-COCRAFT-REPOSITIONING-BRIEF.md",
      "title": "Cocraft: Repositioning Brief, Vocabulary, and Messaging House",
      "date": "2026-02-17",
      "lines": 384,
      "themes": [
        "agents"
      ]
    },
    {
      "file": "2026-02-17-MULTI-AGENT-ARCHITECTURE.md",
      "title": "Multi-Agent Architecture: Participant-Scoped Agents",
      "date": "2026-02-17",
      "lines": 408,
      "themes": [
        "agents",
        "platform_arch"
      ]
    },
    {
      "file": "2026-02-18-SOMEHOW-REPOSITIONING-BRIEF.md",
      "title": "Somehow: Repositioning Brief, Vocabulary, and Messaging House",
      "date": "2026-02-18",
      "lines": 429,
      "themes": [
        "other"
      ]
    },
    {
      "file": "2026-02-19-SANDBOX-AGENT-ACP-MIGRATION.md",
      "title": "Sandbox-Agent v0.1.8 to v0.2.0 ACP Migration Plan",
      "date": "2026-02-19",
      "lines": 1022,
      "themes": [
        "agents"
      ]
    },
    {
      "file": "2026-02-23-DATA-FILE-RENDERING.md",
      "title": "Data File Rendering in Editor",
      "date": "2026-02-23",
      "lines": 206,
      "themes": [
        "other"
      ]
    },
    {
      "file": "2026-02-23-DOCX-FILE-RENDERING.md",
      "title": "Word Document (DOCX) Rendering in Editor",
      "date": "2026-02-23",
      "lines": 241,
      "themes": [
        "other"
      ]
    },
    {
      "file": "2026-02-23-HTML-FILE-RENDERING.md",
      "title": "HTML File Rendering in Editor",
      "date": "2026-02-23",
      "lines": 79,
      "themes": [
        "other"
      ]
    },
    {
      "file": "2026-02-24-MARKDOWN-STYLED-VIEW-IMPROVEMENTS.md",
      "title": "Markdown Styled View Improvements",
      "date": "2026-02-24",
      "lines": 188,
      "themes": [
        "other"
      ]
    },
    {
      "file": "2026-02-26-MEETING-DOCUMENT-VIEW.md",
      "title": "Meeting Document View",
      "date": "2026-02-26",
      "lines": 262,
      "themes": [
        "meetings_voice"
      ]
    },
    {
      "file": "2026-03-02-SESSIONLESS-SPACE-LAZY-COLLAB-SESSIONS.md",
      "title": "Sessionless Space Open + Lazy Collab Session Lifecycle",
      "date": "2026-03-02",
      "lines": 582,
      "themes": [
        "meetings_voice"
      ]
    },
    {
      "file": "2026-03-03-INTENT-DECISION-IMPLEMENTATION-LOOP.md",
      "title": "Closing the Loop: Intent, Decision, Implementation",
      "date": "2026-03-03",
      "lines": 602,
      "themes": [
        "platform_arch"
      ]
    },
    {
      "file": "2026-03-04-PROMPT-BOOKMARKS-AND-AGENT-SKILLS.md",
      "title": "Prompt Bookmarks and Custom Agent Skills",
      "date": "2026-03-04",
      "lines": 91,
      "themes": [
        "agents"
      ]
    },
    {
      "file": "2026-03-04-SANDBOX-AGENT-V021-MIGRATION.md",
      "title": "Sandbox-Agent v0.1.8 to v0.2.1 Migration Plan",
      "date": "2026-03-04",
      "lines": 1014,
      "themes": [
        "agents"
      ]
    },
    {
      "file": "2026-03-04-V2-ACP-CAPABILITIES-RESEARCH.md",
      "title": "V2 ACP Capabilities Research",
      "date": "2026-03-04",
      "lines": 416,
      "themes": [
        "agents",
        "platform_arch"
      ]
    },
    {
      "file": "2026-03-05-TRANSCRIPTION-ARCHITECTURE-OPTIONS.md",
      "title": "Transcription Architecture: Agent Replacement Options",
      "date": "2026-03-05",
      "lines": 276,
      "themes": [
        "agents",
        "meetings_voice",
        "platform_arch"
      ]
    },
    {
      "file": "2026-03-06-ELEVATING-METADATA-TO-INDEX.md",
      "title": "Elevating New Metadata Through the Stack While Preserving Lazy Loading",
      "date": "2026-03-06",
      "lines": 320,
      "themes": [
        "crdt",
        "platform_arch"
      ]
    },
    {
      "file": "2026-03-08-DELETED-FILES-FEATURE-REVIEW.md",
      "title": "Deleted Files Feature: Review",
      "date": "2026-03-08",
      "lines": 482,
      "themes": [
        "ui_ux",
        "cli_terminal"
      ]
    },
    {
      "file": "2026-03-09-BLOB-SUPPORT-INTENT-WEB.md",
      "title": "Blob Support for Intent Web",
      "date": "2026-03-09",
      "lines": 193,
      "themes": [
        "crdt",
        "cli_terminal"
      ]
    },
    {
      "file": "2026-03-09-diff-accept-reject.md",
      "title": "Diff Accept/Reject in Workspace Markdown Files",
      "date": "2026-03-09",
      "lines": 147,
      "themes": [
        "agents"
      ]
    },
    {
      "file": "2026-03-10-CONVERGENCE-UI-REDESIGN.md",
      "title": "Convergence UI Redesign",
      "date": "2026-03-10",
      "lines": 95,
      "themes": [
        "ui_ux",
        "meetings_voice"
      ]
    },
    {
      "file": "2026-03-12-CONVERGENCE-SCANNABILITY-AND-APPLY-TARGETING.md",
      "title": "Convergence Scannability and Apply Targeting",
      "date": "2026-03-12",
      "lines": 56,
      "themes": [
        "other"
      ]
    },
    {
      "file": "2026-03-13-TOPICS-REDESIGN.md",
      "title": "Topics Redesign",
      "date": "2026-03-13",
      "lines": 135,
      "themes": [
        "meetings_voice"
      ]
    },
    {
      "file": "2026-03-14-CLI-FEATURE-FLAGGING-EDITION-BUILDS.md",
      "title": "Intent CLI Feature Flagging & Edition Builds",
      "date": "2026-03-14",
      "lines": 416,
      "themes": [
        "cli_terminal"
      ]
    },
    {
      "file": "2026-03-14-INTENT-WEB-TESTING-STRATEGY.md",
      "title": "Intent-Web Testing Strategy",
      "date": "2026-03-14",
      "lines": 592,
      "themes": [
        "meetings_voice"
      ]
    },
    {
      "file": "2026-03-17-CROSS-PROJECT-FILE-ACCESS.md",
      "title": "Cross-Project File Access for Agents",
      "date": "2026-03-17",
      "lines": 63,
      "themes": [
        "agents"
      ]
    },
    {
      "file": "2026-03-19-SPACE-PLUGINS-SECUREEXEC.md",
      "title": "Space Plugins: Live-Programmable Workspaces via secureexec",
      "date": "2026-03-19",
      "lines": 1225,
      "themes": [
        "crdt"
      ]
    },
    {
      "file": "2026-03-20-SPACE-PLUGINS-ARCHITECTURE-V2.md",
      "title": "Space Plugins Architecture v2",
      "date": "2026-03-20",
      "lines": 395,
      "themes": [
        "platform_arch"
      ]
    },
    {
      "file": "2026-03-21-SANDBOX-AGENT-040-UPGRADE.md",
      "title": "Sandbox Agent v0.2.1 → v0.4.0 Upgrade: Feature Mapping & Agent Feedback Improvements",
      "date": "2026-03-21",
      "lines": 457,
      "themes": [
        "agents"
      ]
    },
    {
      "file": "2026-03-22-MERCH-STORE-DESIGN.md",
      "title": "Merch Store: merch.withstoa.com",
      "date": "2026-03-22",
      "lines": 460,
      "themes": [
        "other"
      ]
    },
    {
      "file": "2026-03-23-CLI-TOPICS-AND-MEETING-SEARCH.md",
      "title": "CLI Topics & Meeting Search",
      "date": "2026-03-23",
      "lines": 292,
      "themes": [
        "agents",
        "meetings_voice",
        "cli_terminal"
      ]
    },
    {
      "file": "2026-03-23-MEETING-NARRATIVE-AND-SEARCH-RESULTS.md",
      "title": "Meeting Narrative Generation & Search Results View",
      "date": "2026-03-23",
      "lines": 239,
      "themes": [
        "meetings_voice"
      ]
    },
    {
      "file": "2026-03-23-SUPPORT-SLACK-BOT-INTEGRATION.md",
      "title": "Support Slack Bot Integration",
      "date": "2026-03-23",
      "lines": 614,
      "themes": [
        "other"
      ]
    },
    {
      "file": "2026-03-24-UNIFIED-AUTH-REFACTOR-DESIGN.md",
      "title": "Unified Auth Refactor Design",
      "date": "2026-03-24",
      "lines": 811,
      "themes": [
        "billing_auth"
      ]
    },
    {
      "file": "2026-03-25-FOCUS-DOCS-TOPICS-UX-FIXES.md",
      "title": "Focus Docs & Topics UX Fixes",
      "date": "2026-03-25",
      "lines": 288,
      "themes": [
        "ui_ux",
        "meetings_voice"
      ]
    },
    {
      "file": "2026-03-29-MEET-WITHSTOA-MIGRATION-PLAN.md",
      "title": "Migration Plan: New Stack for meet.withstoa.com + Dev/Prod Split",
      "date": "2026-03-29",
      "lines": 1117,
      "themes": [
        "other"
      ]
    },
    {
      "file": "2026-03-29-TRANSCRIPTION-EXCELLENCE-FROM-MINUTES.md",
      "title": "Transcription Excellence: Ideas from Minutes for Intent",
      "date": "2026-03-29",
      "lines": 598,
      "themes": [
        "meetings_voice",
        "desktop"
      ]
    },
    {
      "file": "2026-03-30-DASHBOARD-REMOVAL-PLAN.md",
      "title": "Dashboard Removal Plan",
      "date": "2026-03-30",
      "lines": 151,
      "themes": [
        "other"
      ]
    },
    {
      "file": "2025-11-1-EVENT-BUS-ARCHITECTURE.md",
      "title": "Event Bus & Async Persistence Architecture",
      "date": "2026-03-31",
      "lines": 560,
      "themes": [
        "platform_arch"
      ]
    },
    {
      "file": "2025-11-14_TIMELINE_DESIGN.md",
      "title": "Timeline Tab Implementation Design",
      "date": "2026-03-31",
      "lines": 214,
      "themes": [
        "ui_ux",
        "version_history"
      ]
    },
    {
      "file": "2026-03-31-INTENT-CLI-NODE-BRIDGE-PARITY.md",
      "title": "Intent CLI Node Bridge Parity Design",
      "date": "2026-03-31",
      "lines": 354,
      "themes": [
        "crdt",
        "cli_terminal"
      ]
    },
    {
      "file": "FLYIO.MD",
      "title": "1. Create the Fly app (once)",
      "date": "2026-03-31",
      "lines": 141,
      "themes": [
        "p2p_sync"
      ]
    },
    {
      "file": "LESSONS-FROM-TNYOFFICE.md",
      "title": "Lessons from tnyOffice Implementation",
      "date": "2026-03-31",
      "lines": 518,
      "themes": [
        "crdt",
        "platform_arch"
      ]
    },
    {
      "file": "MULTI-USER-MARKDOWN-SYNC.md",
      "title": "Multi-User Markdown Collaboration",
      "date": "2026-03-31",
      "lines": 378,
      "themes": [
        "crdt",
        "p2p_sync"
      ]
    },
    {
      "file": "TEST_PROVENANCE.md",
      "title": "TEST_PROVENANCE.md",
      "date": "2026-03-31",
      "lines": 40,
      "themes": [
        "other"
      ]
    },
    {
      "file": "WEB-EDITOR-USER-FLOW.md",
      "title": "Web Editor User Flow & Information Architecture",
      "date": "2026-03-31",
      "lines": 573,
      "themes": [
        "platform_arch"
      ]
    },
    {
      "file": "event-journal-rearchitecture.md",
      "title": "Event Journal Rearchitecture",
      "date": "2026-03-31",
      "lines": 1848,
      "themes": [
        "crdt",
        "platform_arch"
      ]
    },
    {
      "file": "meeting-search-requirements.md",
      "title": "Meeting Search Requirements",
      "date": "2026-03-31",
      "lines": 245,
      "themes": [
        "meetings_voice"
      ]
    },
    {
      "file": "2026-04-03-SPACE-AGENT-HYBRID-VIRTUAL-FILESYSTEM.md",
      "title": "Space Agent Hybrid Virtual Filesystem",
      "date": "2026-04-03",
      "lines": 814,
      "themes": [
        "agents"
      ]
    },
    {
      "file": "2026-04-04-SPACE-AGENT-SANDBOX-SPEED-AND-CONSISTENCY.md",
      "title": "Space Agent Sandbox Speed And Consistency",
      "date": "2026-04-04",
      "lines": 841,
      "themes": [
        "agents"
      ]
    },
    {
      "file": "2026-04-06-TEMPLATE-SPACE-DOCUMENT-CLONING.md",
      "title": "Template Space Document Cloning",
      "date": "2026-04-06",
      "lines": 179,
      "themes": [
        "other"
      ]
    },
    {
      "file": "2026-04-06-WORKTHREADS-COMPARISON.md",
      "title": "Workthreads Design Comparison",
      "date": "2026-04-06",
      "lines": 400,
      "themes": [
        "other"
      ]
    },
    {
      "file": "2026-04-06-WORKTHREADS.md",
      "title": "Workthreads",
      "date": "2026-04-06",
      "lines": 732,
      "themes": [
        "meetings_voice"
      ]
    },
    {
      "file": "2026-04-06-WORKTHREADS2.md",
      "title": "Workthreads — Design Document",
      "date": "2026-04-06",
      "lines": 359,
      "themes": [
        "agents",
        "meetings_voice"
      ]
    },
    {
      "file": "2026-04-07-HTML-RENDERER-RELATIVE-ASSET-RESOLUTION.md",
      "title": "HTML Renderer — Relative Asset Resolution",
      "date": "2026-04-07",
      "lines": 193,
      "themes": [
        "other"
      ]
    },
    {
      "file": "2026-04-07-ONBOARDING-EMAIL-ARCHITECTURE.md",
      "title": "Onboarding Email Architecture",
      "date": "2026-04-07",
      "lines": 315,
      "themes": [
        "platform_arch"
      ]
    },
    {
      "file": "2026-04-07-STARTER-SPACE-PUBLISH-AND-CLONE.md",
      "title": "Starter Space — Publish & Clone",
      "date": "2026-04-07",
      "lines": 464,
      "themes": [
        "other"
      ]
    },
    {
      "file": "2026-04-07-WEB-FEATURE-FLAGS-VERCEL-SDK.md",
      "title": "Web Feature Flags with Vercel Flags SDK",
      "date": "2026-04-07",
      "lines": 875,
      "themes": [
        "agents",
        "platform_arch"
      ]
    },
    {
      "file": "2026-04-08-WORKTHREADS-V1-PLAN.md",
      "title": "Workthreads — Final Design",
      "date": "2026-04-08",
      "lines": 191,
      "themes": [
        "meetings_voice"
      ]
    },
    {
      "file": "2026-04-10-TEAM-INVITE-AND-ACTIVATION-STRATEGY.md",
      "title": "Team Invite & Activation Strategy",
      "date": "2026-04-10",
      "lines": 331,
      "themes": [
        "other"
      ]
    },
    {
      "file": "2026-04-10-WORKTHREADS-REPRESENTATION.md",
      "title": "Workthreads — Filesystem and Web Representation",
      "date": "2026-04-10",
      "lines": 1066,
      "themes": [
        "agents"
      ]
    },
    {
      "file": "2026-04-13-LIVE-CLI-AGENT-PRESENCE-IN-MEETINGS.md",
      "title": "Live CLI Agent Presence in Meetings",
      "date": "2026-04-13",
      "lines": 220,
      "themes": [
        "agents",
        "meetings_voice",
        "cli_terminal"
      ]
    },
    {
      "file": "2026-04-14-CREDIT-EXPIRATION-AND-NON-REFUNDABLE.md",
      "title": "Credit Expiration and Non-Refundable Policy",
      "date": "2026-04-14",
      "lines": 560,
      "themes": [
        "agents",
        "billing_auth"
      ]
    },
    {
      "file": "2026-04-14-PRELAUNCH-PERFORMANCE-KISS-PLAN.md",
      "title": "Pre-Launch Performance KISS Plan",
      "date": "2026-04-14",
      "lines": 365,
      "themes": [
        "other"
      ]
    },
    {
      "file": "2026-04-16-COMMUNITY-FORUM-DESIGN.md",
      "title": "Community Forum Design (Discourse-Style, Cross-Org + Public)",
      "date": "2026-04-16",
      "lines": 1093,
      "themes": [
        "agents",
        "community_forum"
      ]
    },
    {
      "file": "2026-04-16-WEB-RENAME-AS-DELETE-PLUS-CREATE.md",
      "title": "Web Rename as Delete + Create",
      "date": "2026-04-16",
      "lines": 165,
      "themes": [
        "crdt",
        "cli_terminal",
        "platform_arch"
      ]
    },
    {
      "file": "2026-04-17-RESTORE-VERSION-UX.md",
      "title": "Restore to This Version — UX Plan",
      "date": "2026-04-17",
      "lines": 144,
      "themes": [
        "ui_ux"
      ]
    },
    {
      "file": "2026-04-18-COMMUNITY-FORUM-IA-MOCKS.md",
      "title": "Community Forum IA Mocks",
      "date": "2026-04-18",
      "lines": 757,
      "themes": [
        "community_forum"
      ]
    }
  ]
}
